{"catalogueName":"BBMRI","catalogueAddress":"https://dor.erdri.mig-frankfurt.de/rest/registries/search","catalogueType":["biobank"],"created":1596441107857,"_id":"CU6F3ZSRB"}
{"catalogueName":"Orphanet","catalogueAddress":"https://dor.erdri.mig-frankfurt.de/rest/registries/search","catalogueType":["registry","biobank"],"created":1596188657496,"_id":"RLDL66TEV"}
{"catalogueName":"ERDRI.dor","catalogueAddress":"https://dor.erdri.mig-frankfurt.de/rest/registries/search","catalogueType":["registry"],"created":1596526555496,"_id":"RPR2ZDA1N"}
